pypassfusion/__init__.py
pypassfusion/main.py
pypassfusion/menu.py
pypassfusion-1.5.1.5.dist-info/METADATA
pypassfusion-1.5.1.5.dist-info/WHEEL
pypassfusion-1.5.1.5.dist-info/entry_points.txt
pypassfusion-1.5.1.5.dist-info/top_level.txt
pypassfusion-1.5.1.5.dist-info/RECORD
