Metadata-Version: 2.1
Name: pypassfusion
Version: 1.5.1.5
Summary: The password generator Python app is a simple and efficient tool for creating strong and secure passwords
Author: Amir Hossein Bonyadi
Author-email: bonyadi.amirhosein@gmail.com
Keywords: python,password,generator,Passgenerator,pypassgenerator
Classifier: Intended Audience :: End Users/Desktop
Classifier: Programming Language :: Python :: 3
Classifier: Operating System :: Unix
Classifier: Operating System :: MacOS
Classifier: Operating System :: Microsoft :: Windows
Requires-Dist: tk
